netscaler_exporter/__init__.py
netscaler_exporter/build_conf.py
netscaler_exporter/collector.py
netscaler_exporter/constants.py
netscaler_exporter/core_exporter.py
netscaler_exporter/filters.py
netscaler_exporter/netscaler_api.py
netscaler_exporter/netscaler_exporter.py
netscaler_exporter/yamlscript.py
netscaler_exporter/conf/netscaler_exporter.yml
netscaler_exporter/conf/metrics/aaa.yml
netscaler_exporter/conf/metrics/csvserver.yml
netscaler_exporter/conf/metrics/hanode.yml
netscaler_exporter/conf/metrics/interface.yml
netscaler_exporter/conf/metrics/lbvserver.yml
netscaler_exporter/conf/metrics/ns.yml
netscaler_exporter/conf/metrics/nscapacity.yml
netscaler_exporter/conf/metrics/protocolhttp.yml
netscaler_exporter/conf/metrics/protocolip.yml
netscaler_exporter/conf/metrics/protocoltcp.yml
netscaler_exporter/conf/metrics/protocoludp.yml
netscaler_exporter/conf/metrics/service.yml
netscaler_exporter/conf/metrics/services.yml
netscaler_exporter/conf/metrics/ssl.yml
netscaler_exporter/conf/metrics/sslcertkey.yml
netscaler_exporter/conf/metrics/sslvserver.yml
netscaler_exporter/conf/metrics/system.yml
netscaler_exporter/conf/metrics/systemcpu.yml
netscaler_exporter/conf/metrics/systemmemory.yml
netscaler_exporter/custom_filters/__init__.py
netscaler_exporter/custom_filters/defaults.py
netscaler_exporter/custom_filters/to_timestamp.py
netscaler_exporter-1.1.1.dist-info/METADATA
netscaler_exporter-1.1.1.dist-info/WHEEL
netscaler_exporter-1.1.1.dist-info/entry_points.txt
netscaler_exporter-1.1.1.dist-info/top_level.txt
netscaler_exporter-1.1.1.dist-info/RECORD
